[
    {
        "featureType": "all",
        "elementType": "labels",
        "stylers": [
            {
                "visibility": "on"
            }
        ]
    },
    {
        "featureType": "all",
        "elementType": "labels.text.fill",
        "stylers": [
            {
                "saturation": 36
            },
            {
                "color": "#000000"
            },
            {
                "lightness": 40
            }
        ]
    },
    {
        "featureType": "all",
        "elementType": "labels.text.stroke",
        "stylers": [
            {
                "visibility": "on"
            },
            {
                "color": "#000000"
            },
            {
                "lightness": 16
            }
        ]
    },
    {
        "featureType": "all",
        "elementType": "labels.icon",
        "stylers": [
            {
                "visibility": "off"
            }
        ]
    },
    {
        "featureType": "administrative",
        "elementType": "geometry.fill",
        "stylers": [
            {
                "color": "#000000"
            },
            {
                "lightness": 20
            }
        ]
    },
    {
        "featureType": "administrative",
        "elementType": "geometry.stroke",
        "stylers": [
            {
                "color": "#000000"
            },
            {
                "lightness": 17
            },
            {
                "weight": 1.2
            }
        ]
    },
    {
        "featureType": "administrative.country",
        "elementType": "labels.text.fill",
        "stylers": [
            {
                "color": "#b8b8b8"
            }
        ]
    },
    {
        "featureType": "administrative.locality",
        "elementType": "labels.text.fill",
        "stylers": [
            {
                "color": "#c4c4c4"
            }
        ]
    },
    {
        "featureType": "administrative.neighborhood",
        "elementType": "labels.text.fill",
        "stylers": [
            {
                "color": "#727ebd"
            }
        ]
    },
    {
        "featureType": "administrative.neighborhood",
        "elementType": "labels.text.stroke",
        "stylers": [
            {
                "lightness": "-20"
            }
        ]
    },
    {
        "featureType": "landscape",
        "elementType": "geometry",
        "stylers": [
            {
                "color": "#000000"
            },
            {
                "lightness": "20"
            },
            {
                "visibility": "on"
            }
        ]
    },
    {
        "featureType": "landscape.natural",
        "elementType": "geometry",
        "stylers": [
            {
                "lightness": "8"
            },
            {
                "saturation": "0"
            }
        ]
    },
    {
        "featureType": "poi",
        "elementType": "geometry",
        "stylers": [
            {
                "color": "#000000"
            },
            {
                "lightness": "22"
            },
            {
                "visibility": "on"
            }
        ]
    },
    {
        "featureType": "poi",
        "elementType": "labels.text.fill",
        "stylers": [
            {
                "color": "#b8b8b8"
            }
        ]
    },
    {
        "featureType": "poi.business",
        "elementType": "geometry",
        "stylers": [
            {
                "visibility": "on"
            }
        ]
    },
    {
        "featureType": "road.highway",
        "elementType": "geometry.fill",
        "stylers": [
            {
                "color": "#5e69a2"
            },
            {
                "lightness": "0"
            }
        ]
    },
    {
        "featureType": "road.highway",
        "elementType": "geometry.stroke",
        "stylers": [
            {
                "visibility": "off"
            }
        ]
    },
    {
        "featureType": "road.highway",
        "elementType": "labels.text.fill",
        "stylers": [
            {
                "color": "#ffffff"
            }
        ]
    },
    {
        "featureType": "road.arterial",
        "elementType": "geometry",
        "stylers": [
            {
                "color": "#000000"
            },
            {
                "lightness": "18"
            }
        ]
    },
    {
        "featureType": "road.arterial",
        "elementType": "geometry.fill",
        "stylers": [
            {
                "color": "#72737d"
            },
            {
                "lightness": "0"
            }
        ]
    },
    {
        "featureType": "road.arterial",
        "elementType": "labels.text.fill",
        "stylers": [
            {
                "color": "#ffffff"
            }
        ]
    },
    {
        "featureType": "road.arterial",
        "elementType": "labels.text.stroke",
        "stylers": [
            {
                "color": "#2c2c2c"
            }
        ]
    },
    {
        "featureType": "road.local",
        "elementType": "geometry",
        "stylers": [
            {
                "color": "#000000"
            },
            {
                "lightness": "16"
            },
            {
                "saturation": "0"
            }
        ]
    },
    {
        "featureType": "road.local",
        "elementType": "labels.text.fill",
        "stylers": [
            {
                "color": "#bfbebe"
            }
        ]
    },
    {
        "featureType": "transit",
        "elementType": "geometry",
        "stylers": [
            {
                "color": "#262627"
            },
            {
                "lightness": "0"
            },
            {
                "visibility": "on"
            }
        ]
    },
    {
        "featureType": "transit",
        "elementType": "labels.text.fill",
        "stylers": [
            {
                "color": "#8f8f8f"
            }
        ]
    },
    {
        "featureType": "water",
        "elementType": "geometry",
        "stylers": [
            {
                "color": "#243240"
            },
            {
                "lightness": "0"
            },
            {
                "visibility": "on"
            }
        ]
    },
    {
        "featureType": "water",
        "elementType": "labels.text.fill",
        "stylers": [
            {
                "color": "#6e6e6e"
            }
        ]
    }
]
